{
  "version": "1.2.0-stage2.1",
  "description": "Stage 2.1 production building kit integration. Building kit V1 textures remain enabled with door asset support added as opt-in.",
  "textures": [
    {
      "key": "player_viking_base",
      "type": "image",
      "url": "assets/production/characters/player/player_viking_base_64.png",
      "enabled": false,
      "notes": "Single-frame fallback-ready player art. Keep transparent background."
    },
    {
      "key": "resource_pine_tree",
      "type": "image",
      "url": "assets/production/resources/nodes/resource_pine_tree_64.png",
      "enabled": false,
      "notes": "Pine tree node visual used by tree harvest nodes."
    },
    {
      "key": "resource_stone_boulder",
      "type": "image",
      "url": "assets/production/resources/nodes/resource_stone_boulder_64.png",
      "enabled": false,
      "notes": "Stone boulder node visual used by rock harvest nodes."
    },
    {
      "key": "resource_iron_ore",
      "type": "image",
      "url": "assets/production/resources/nodes/resource_iron_ore_64.png",
      "enabled": false,
      "notes": "Iron ore node visual used by ore harvest nodes."
    },
    {
      "key": "build_wood_floor",
      "type": "image",
      "url": "assets/production/buildings/pieces/build_wood_floor_64.png",
      "enabled": true,
      "notes": "Placed for wood floor pieces. Verified Stage 2 Building Kit V1 texture."
    },
    {
      "key": "build_wood_wall",
      "type": "image",
      "url": "assets/production/buildings/pieces/build_wood_wall_64.png",
      "enabled": true,
      "notes": "Placed for wood wall pieces. Verified Stage 2 Building Kit V1 texture."
    },
    {
      "key": "build_standing_torch",
      "type": "image",
      "url": "assets/production/buildings/pieces/build_standing_torch_64.png",
      "enabled": true,
      "notes": "Placed for standing torch pieces. Verified Stage 2 Building Kit V1 texture."
    },
    {
      "key": "build_spike_wall",
      "type": "image",
      "url": "assets/production/buildings/pieces/build_spike_wall_64.png",
      "enabled": true,
      "notes": "Placed for spike wall pieces. Verified Stage 2 Building Kit V1 texture."
    },
    {
      "key": "build_thatch_roof",
      "type": "image",
      "url": "assets/production/buildings/pieces/build_thatch_roof_64.png",
      "enabled": true,
      "notes": "Placed for thatch roof pieces. Verified Stage 2 Building Kit V1 texture."
    },
    {
      "key": "build_wood_door",
      "type": "image",
      "url": "assets/production/buildings/pieces/build_wood_door_64.png",
      "enabled": false,
      "notes": "Stage 2.1 door support entry. Enable once reviewed production door texture is present."
    }
  ]
}
